floss/__init__.py
floss/__main__.py
floss/api_hooks.py
floss/const.py
floss/decoding_manager.py
floss/function_argument_getter.py
floss/identify.py
floss/logging_.py
floss/main.py
floss/results.py
floss/stackstrings.py
floss/string_decoder.py
floss/strings.py
floss/tightstrings.py
floss/utils.py
floss/version.py
floss/features/__init__.py
floss/features/extract.py
floss/features/features.py
floss/language/__init__.py
floss/language/identify.py
floss/language/utils.py
floss/language/go/__init__.py
floss/language/go/coverage.py
floss/language/go/extract.py
floss/language/rust/__init__.py
floss/language/rust/coverage.py
floss/language/rust/extract.py
floss/language/rust/rust_version_database.py
floss/render/__init__.py
floss/render/default.py
floss/render/json.py
floss/render/sanitize.py
floss/sigs/1_flare_msvc_rtf_32_64.sig
floss/sigs/2_flare_msvc_atlmfc_32_64.sig
floss/sigs/3_flare_common_libs.sig
floss/sigs/README.md
flare_floss-3.1.1.dist-info/LICENSE.txt
flare_floss-3.1.1.dist-info/METADATA
flare_floss-3.1.1.dist-info/WHEEL
flare_floss-3.1.1.dist-info/entry_points.txt
flare_floss-3.1.1.dist-info/top_level.txt
flare_floss-3.1.1.dist-info/RECORD
