Metadata-Version: 2.1
Name: flare-floss
Version: 3.1.1
Summary: FLARE Obfuscated String Solver
Author-email: Willi Ballenthin <william.ballenthin@mandiant.com>, Moritz Raabe <moritz.raabe@mandiant.com>
License: 
Project-URL: Homepage, https://www.github.com/mandiant/flare-floss
Project-URL: Repository, https://www.github.com/mandiant/flare-floss.git
Project-URL: Documentation, https://github.com/mandiant/flare-floss/tree/master/doc
Project-URL: Signatures, https://github.com/mandiant/flare-floss/tree/master/floss/sigs
Keywords: floss,malware,analysis,obfuscation,strings,FLARE
Classifier: Development Status :: 5 - Production/Stable
Classifier: Intended Audience :: Developers
Classifier: Intended Audience :: Information Technology
Classifier: License :: OSI Approved :: Apache Software License
Classifier: Natural Language :: English
Classifier: Programming Language :: Python :: 3
Classifier: Topic :: Security
Requires-Python: >=3.8
License-File: LICENSE.txt
Requires-Dist: tabulate >=0.9
Requires-Dist: pydantic >=2
Requires-Dist: tqdm >=4
Requires-Dist: halo >=0.0.31
Requires-Dist: rich >=13
Requires-Dist: pefile >=2022.5.30
Requires-Dist: binary2strings >=0.1
Requires-Dist: viv-utils[flirt] >=0.7.9
Requires-Dist: vivisect >=1.1.1
Requires-Dist: dncil >=1.0.2
Requires-Dist: networkx <3.2,>=3
Provides-Extra: build
Requires-Dist: pyinstaller ==6.8.0 ; extra == 'build'
Requires-Dist: setuptools ==75.1.0 ; extra == 'build'
Requires-Dist: build ==1.2.1 ; extra == 'build'
Provides-Extra: dev
Requires-Dist: pre-commit ==3.5.0 ; extra == 'dev'
Requires-Dist: pyyaml ==6.0.1 ; extra == 'dev'
Requires-Dist: pytest ==8.3.3 ; extra == 'dev'
Requires-Dist: pytest-sugar ==1.0.0 ; extra == 'dev'
Requires-Dist: pytest-instafail ==0.5.0 ; extra == 'dev'
Requires-Dist: pytest-cov ==5.0.0 ; extra == 'dev'
Requires-Dist: pycodestyle ==2.11.1 ; extra == 'dev'
Requires-Dist: black ==24.4.2 ; extra == 'dev'
Requires-Dist: isort ==5.13.2 ; extra == 'dev'
Requires-Dist: mypy ==1.10.0 ; extra == 'dev'
Requires-Dist: types-PyYAML ==6.0.10 ; extra == 'dev'
Requires-Dist: types-tabulate ==0.9.0.20240106 ; extra == 'dev'
